qr_generator/__init__.py
qr_generator/qr_generate.py
genqr-1.3.dist-info/METADATA
genqr-1.3.dist-info/WHEEL
genqr-1.3.dist-info/top_level.txt
genqr-1.3.dist-info/RECORD
