Metadata-Version: 2.1
Name: genqr
Version: 1.3
Summary: A simple QR code generator
Home-page: https://github.com/mjfactor/Qr-Code-Generator
Author: Mjfactor
Classifier: Development Status :: 3 - Alpha
Classifier: Intended Audience :: Developers
Classifier: License :: OSI Approved :: MIT License
Classifier: Programming Language :: Python
Classifier: Programming Language :: Python :: 3
Classifier: Programming Language :: Python :: 3.6
Classifier: Programming Language :: Python :: 3.7
Classifier: Programming Language :: Python :: 3.8
Classifier: Programming Language :: Python :: 3.9
Requires-Python: >=3.6
Requires-Dist: qrcode[pil]
